{"index.md":"k85_mjbY","markdown_adapter_apis.md":"fhy5ZGaZ","markdown_adapter_config.md":"CPWDXrQu","markdown_adapter_development-docs.md":"SAux1QOA","markdown_adapter_development.md":"Ch8e8Nqg","markdown_adapter_errorcodes.md":"PMuoA9in","markdown_adapter_events.md":"aU9CIOWV","markdown_adapter_faq.md":"ChZqc9xX","markdown_adapter_issues.md":"8OF64W5o","markdown_iirose_dev_actions.md":"VTEzCPcn","markdown_iirose_dev_administration.md":"08DVMHeE","markdown_iirose_dev_after-login.md":"fjF8kEz0","markdown_iirose_dev_connection.md":"DnfeiJD0","markdown_iirose_dev_events.md":"mdDI4lRJ","markdown_iirose_dev_financial.md":"CE4jCC7y","markdown_iirose_dev_login.md":"D_2hRH2e","markdown_iirose_dev_media.md":"CJPwzb6M","markdown_iirose_dev_messages.md":"DixJnb3a","markdown_iirose_introduce.md":"CsKYM9yM","markdown_iirose_introduction_1.md":"BQ8hGxXD","markdown_iirose_introduction_2.md":"cm0hRsO5","markdown_iirose_introduction_3.md":"DcGvLwNE","markdown_iirose_introduction_4.md":"DEmxVf2S","markdown_iirose_introduction_5.md":"CPelkDjS","markdown_platform-access-guide_assets.md":"D8R1YNoR","markdown_platform-access-guide_koishi.md":"DzCzT3av","markdown_platform-access-guide_start.md":"CX-zkC49","markdown_plugins_0.md":"Z-_oIK0C"}
